{
  "main": {
    "id": "9849becc57480751",
    "type": "split",
    "children": [
      {
        "id": "ec870941d6d9ea72",
        "type": "tabs",
        "children": [
          {
            "id": "988e4f5ed3b490cb",
            "type": "leaf",
            "state": {
              "type": "empty",
              "state": {}
            }
          }
        ]
      }
    ],
    "direction": "vertical"
  },
  "left": {
    "id": "35c4d1b40f4da472",
    "type": "split",
    "children": [
      {
        "id": "a0b0d81d9792983b",
        "type": "tabs",
        "children": [
          {
            "id": "060710f5e78e7906",
            "type": "leaf",
            "state": {
              "type": "file-explorer",
              "state": {
                "sortOrder": "alphabetical"
              }
            }
          },
          {
            "id": "1d2b859dbba4e304",
            "type": "leaf",
            "state": {
              "type": "search",
              "state": {
                "query": "",
                "matchingCase": false,
                "explainSearch": false,
                "collapseAll": false,
                "extraContext": false,
                "sortOrder": "alphabetical"
              }
            }
          },
          {
            "id": "364681acfc9b8e84",
            "type": "leaf",
            "state": {
              "type": "bookmarks",
              "state": {}
            }
          }
        ]
      }
    ],
    "direction": "horizontal",
    "width": 300
  },
  "right": {
    "id": "02d8e6f64b87e509",
    "type": "split",
    "children": [
      {
        "id": "7924bfe737608dbb",
        "type": "tabs",
        "children": [
          {
            "id": "9d3f8b78c927cea0",
            "type": "leaf",
            "state": {
              "type": "backlink",
              "state": {
                "collapseAll": false,
                "extraContext": false,
                "sortOrder": "alphabetical",
                "showSearch": false,
                "searchQuery": "",
                "backlinkCollapsed": false,
                "unlinkedCollapsed": true
              }
            }
          },
          {
            "id": "17c4d1a17a7658f4",
            "type": "leaf",
            "state": {
              "type": "outgoing-link",
              "state": {
                "linksCollapsed": false,
                "unlinkedCollapsed": true
              }
            }
          },
          {
            "id": "8189120380efa7dd",
            "type": "leaf",
            "state": {
              "type": "tag",
              "state": {
                "sortOrder": "frequency",
                "useHierarchy": true
              }
            }
          },
          {
            "id": "6d19d5e149b895f9",
            "type": "leaf",
            "state": {
              "type": "outline",
              "state": {}
            }
          }
        ]
      }
    ],
    "direction": "horizontal",
    "width": 300,
    "collapsed": true
  },
  "left-ribbon": {
    "hiddenItems": {
      "switcher:Open quick switcher": false,
      "graph:Open graph view": false,
      "canvas:Create new canvas": false,
      "daily-notes:Open today's daily note": false,
      "templates:Insert template": false,
      "command-palette:Open command palette": false
    }
  },
  "active": "988e4f5ed3b490cb",
  "lastOpenFiles": [
    "content/python/_index.md",
    "content/python/basics.md",
    "content/python",
    "content/cybersecurity/_index.md",
    "content/networking/_index.md",
    "content/networking/newccnanotes/part3.md",
    "content/networking/newccnanotes/part2.md",
    "content/networking/newccnanotes/part1.md",
    "content/networking/newccnanotes/9spanningtreeprotocolconcepts.md",
    "content/networking/newccnanotes/8vlans.md",
    "content/networking/newccnanotes/7switchinterfaces.md",
    "content/networking/newccnanotes/6management.md",
    "content/networking/newccnanotes/5switching.md",
    "content/networking/newccnanotes/4cli.md",
    "content/networking/newccnanotes/3wansandiprouting.md",
    "content/networking/newccnanotes/2ethernetlans.md",
    "content/networking/newccnanotes/1tcpipbasic.md",
    "content/networking/newccnanotes/19ansiblepuppetchef.md",
    "content/networking/newccnanotes/18restandjson.md",
    "content/networking/newccnanotes/17softwaredefinedaccess.md",
    "content/networking/newccnanotes/16controllerbasednetworking.md",
    "content/networking/newccnanotes/15routeroperation.md",
    "content/networking/newccnanotes/15cloudarchitecture.md",
    "content/networking/newccnanotes/14wanarchitecture.md",
    "content/networking/newccnanotes/12classfulipv4.md",
    "content/networking/juniper/toggle_poe.md",
    "content/networking/newccnanotes/10rstpandetherchannel.md",
    "content/networking/newccnanotes",
    "content/networking/juniper",
    "content/networking/cisco",
    "content/networking",
    "content/linux/misc_linux",
    "content/linux/rhcsa",
    "content/linux/The_Linux_Command_Line",
    "content/linux",
    "content/cybersecurity"
  ]
}